felix_library/__init__.py
felix_library/hw2.py
felix_library/main.py
felix_library/other.py
felix_library/other_method.py
felixlibrary-1.0.1.dist-info/LICENCE.txt
felixlibrary-1.0.1.dist-info/METADATA
felixlibrary-1.0.1.dist-info/WHEEL
felixlibrary-1.0.1.dist-info/top_level.txt
felixlibrary-1.0.1.dist-info/RECORD
